AUTHORS.txt
CHANGES.txt
LICENSE.txt
MANIFEST.in
README.rst
setup.py
tests/__init__.py
tests/main.py
wurfl_python/__init__.py
wurfl_python/constants.py
wurfl_python/exceptions.py
wurfl_python/processor.py
wurfl_python.egg-info/PKG-INFO
wurfl_python.egg-info/SOURCES.txt
wurfl_python.egg-info/dependency_links.txt
wurfl_python.egg-info/entry_points.txt
wurfl_python.egg-info/requires.txt
wurfl_python.egg-info/top_level.txt
wurfl_python/handlers/__init__.py
wurfl_python/handlers/matchers/__init__.py
wurfl_python/handlers/matchers/ld.py
wurfl_python/handlers/matchers/ris.py
wurfl_python/normalizers/__init__.py
wurfl_python/normalizers/generic.py
wurfl_python/normalizers/specific.py