Metadata-Version: 1.1
Name: wurfl-python
Version: 0.1
Summary: WURFL Python: matching user agent strings with devices in the WURFL database using Python.
Home-page: https://github.com/carlosabalde/wurfl-python
Author: Carlos Abalde
Author-email: carlos.abalde@gmail.com
License: GPL
Platform: UNKNOWN
Classifier: Framework :: Django
Classifier: Intended Audience :: Developers
Classifier: Intended Audience :: System Administrators
Classifier: Operating System :: OS Independent
